edstan/__init__.py
edstan/mcmc.py
edstan/model.py
edstan/data/2pl_latent_reg.stan
edstan/data/gpcm_latent_reg.stan
edstan/data/grsm_latent_reg.stan
edstan/data/pcm_latent_reg.stan
edstan/data/rasch_latent_reg.stan
edstan/data/rsm_latent_reg.stan
edstan-0.2.0.dist-info/METADATA
edstan-0.2.0.dist-info/WHEEL
edstan-0.2.0.dist-info/top_level.txt
edstan-0.2.0.dist-info/RECORD
