Metadata-Version: 2.4
Name: edstan
Version: 0.2.0
Summary: Streamlines the fitting of common Bayesian item response theory models using Stan
Author-email: "Daniel C. Furr" <danielcfurr@berkeley.edu>
License: MIT
Project-URL: Homepage, https://github.com/danielcfurr/edstan-python
Classifier: Programming Language :: Python :: 3
Classifier: License :: OSI Approved :: MIT License
Classifier: Operating System :: OS Independent
Requires-Python: >=3.8
